openg2p_sr_celery_workers/__init__.py
openg2p_sr_celery_workers/app.py
openg2p_sr_celery_workers/config.py
openg2p_sr_celery_workers/helpers/__init__.py
openg2p_sr_celery_workers/helpers/oauth_token.py
openg2p_sr_celery_workers/tasks/__init__.py
openg2p_sr_celery_workers/tasks/id_generation_request.py
openg2p_sr_celery_workers/tasks/id_generation_update.py
openg2p_sr_celery_workers-1.0.1.dist-info/METADATA
openg2p_sr_celery_workers-1.0.1.dist-info/WHEEL
openg2p_sr_celery_workers-1.0.1.dist-info/RECORD
