Metadata-Version: 2.3
Name: openg2p-sr-celery-workers
Version: 1.0.1
Summary: OpenG2P Social Registry Celery Workers
Project-URL: Homepage, https://openg2p.org
Project-URL: Documentation, https://docs.openg2p.org/
Project-URL: Repository, https://github.com/OpenG2P/openg2p-social-registry-bg-tasks
Project-URL: Source, https://github.com/OpenG2P/openg2p-social-registry-bg-tasks
Author-email: OpenG2P <info@openg2p.org>
Classifier: License :: OSI Approved :: Mozilla Public License 2.0 (MPL 2.0)
Classifier: Operating System :: OS Independent
Classifier: Programming Language :: Python :: 3
Requires-Python: >=3.7
Requires-Dist: celery
Requires-Dist: openg2p-fastapi-auth
Requires-Dist: openg2p-fastapi-common
